crop_coach/__init__.py
crop_coach/default_data/WLP_NPK.conf
crop_coach/default_data/agro.yaml
crop_coach/default_data/crop.cab
crop_coach/default_data/site.cab
crop_coach/default_data/soil.cab
crop_coach/envs/__init__.py
crop_coach/envs/actions.py
crop_coach/envs/models.py
crop_coach/envs/reward.py
crop_coach/envs/wofost_env.py
crop_coach/envs/pcse/__init__.py
crop_coach/envs/pcse/agromanager.py
crop_coach/envs/pcse/decorators.py
crop_coach/envs/pcse/empty_model.py
crop_coach/envs/pcse/engine.py
crop_coach/envs/pcse/exceptions.py
crop_coach/envs/pcse/models.py
crop_coach/envs/pcse/signals.py
crop_coach/envs/pcse/start_wofost.py
crop_coach/envs/pcse/taskmanager.py
crop_coach/envs/pcse/timer.py
crop_coach/envs/pcse/traitlets.py
crop_coach/envs/pcse/util.py
crop_coach/envs/pcse/base/__init__.py
crop_coach/envs/pcse/base/dispatcher.py
crop_coach/envs/pcse/base/engine.py
crop_coach/envs/pcse/base/parameter_providers.py
crop_coach/envs/pcse/base/simulationobject.py
crop_coach/envs/pcse/base/states_rates.py
crop_coach/envs/pcse/base/variablekiosk.py
crop_coach/envs/pcse/base/weather.py
crop_coach/envs/pcse/conf/__init__.py
crop_coach/envs/pcse/crop/__init__.py
crop_coach/envs/pcse/crop/abioticdamage.py
crop_coach/envs/pcse/crop/assimilation.py
crop_coach/envs/pcse/crop/evapotranspiration.py
crop_coach/envs/pcse/crop/greenlayercrop.py
crop_coach/envs/pcse/crop/leaf_dynamics.py
crop_coach/envs/pcse/crop/lintul3.py
crop_coach/envs/pcse/crop/npk_dynamics.py
crop_coach/envs/pcse/crop/partitioning.py
crop_coach/envs/pcse/crop/phenology.py
crop_coach/envs/pcse/crop/respiration.py
crop_coach/envs/pcse/crop/root_dynamics.py
crop_coach/envs/pcse/crop/stem_dynamics.py
crop_coach/envs/pcse/crop/storage_organ_dynamics.py
crop_coach/envs/pcse/crop/wofost.py
crop_coach/envs/pcse/crop/wofost_npk.py
crop_coach/envs/pcse/crop/wofost_winterkill.py
crop_coach/envs/pcse/crop/nutrients/__init__.py
crop_coach/envs/pcse/crop/nutrients/npk_demand_uptake.py
crop_coach-0.0.8.dist-info/METADATA
crop_coach-0.0.8.dist-info/WHEEL
crop_coach-0.0.8.dist-info/top_level.txt
crop_coach-0.0.8.dist-info/RECORD
