Metadata-Version: 2.1
Name: crop-coach
Version: 0.0.8
Summary: crop_coach : A crop growth simulation model turn into OpenAI Gym environment
Author: AgriEdge (Noureddine Ech-chouky)
Author-email: <noureddine.echchuky@um5r.ac.ma>
Keywords: python,Reinforcement learning,gym environment,pcse,crop management,precision agriculture,wofost
Classifier: Development Status :: 1 - Planning
Classifier: Intended Audience :: Developers
Classifier: Programming Language :: Python :: 3.8
Classifier: Operating System :: Unix
Classifier: Operating System :: MacOS :: MacOS X
Classifier: Operating System :: Microsoft :: Windows
Requires-Dist: gym
Requires-Dist: shutup
Requires-Dist: traitlets-pcse
Requires-Dist: sqlalchemy
Requires-Dist: PyYAML
Requires-Dist: pandas
Requires-Dist: requests
Requires-Dist: xlrd
Requires-Dist: scienceplots
